audio8/__init__.py
audio8/convert_wav2vec2_checkpoint.py
audio8/ctc.py
audio8/data.py
audio8/pretrain.py
audio8/pretrain_paired.py
audio8/test.py
audio8/text.py
audio8/train.py
audio8/train_seq2seq.py
audio8/utils.py
audio8/version.py
audio8/wav2vec2.py
audio8/wrd2bpe.py
mead_audio8-0.0.6.data/scripts/pretrain.py
mead_audio8-0.0.6.data/scripts/pretrain_paired.py
mead_audio8-0.0.6.data/scripts/test.py
mead_audio8-0.0.6.data/scripts/train.py
mead_audio8-0.0.6.dist-info/METADATA
mead_audio8-0.0.6.dist-info/WHEEL
mead_audio8-0.0.6.dist-info/top_level.txt
mead_audio8-0.0.6.dist-info/RECORD
